PythonShujujiegouYuSuanfa/README.md
PythonShujujiegouYuSuanfa/__init__.py
PythonShujujiegouYuSuanfa/__main__.py
PythonShujujiegouYuSuanfa/file.epub
PythonShujujiegouYuSuanfa/index.html
PythonShujujiegouYuSuanfa/css/__init__.py
PythonShujujiegouYuSuanfa/css/annotations.css
PythonShujujiegouYuSuanfa/css/main.css
PythonShujujiegouYuSuanfa/css/normalize.css
PythonShujujiegouYuSuanfa/css/popup.css
PythonShujujiegouYuSuanfa/font/__init__.py
PythonShujujiegouYuSuanfa/font/fontello.eot
PythonShujujiegouYuSuanfa/font/fontello.svg
PythonShujujiegouYuSuanfa/font/fontello.ttf
PythonShujujiegouYuSuanfa/font/fontello.woff
PythonShujujiegouYuSuanfa/img/__init__.py
PythonShujujiegouYuSuanfa/img/annotator-glyph-sprite.png
PythonShujujiegouYuSuanfa/img/annotator-icon-sprite.png
PythonShujujiegouYuSuanfa/img/apple-touch-icon.png
PythonShujujiegouYuSuanfa/img/cancelfullscreen.png
PythonShujujiegouYuSuanfa/img/close.png
PythonShujujiegouYuSuanfa/img/fullscreen.png
PythonShujujiegouYuSuanfa/img/loader.gif
PythonShujujiegouYuSuanfa/img/menu-icon.png
PythonShujujiegouYuSuanfa/img/save.png
PythonShujujiegouYuSuanfa/img/saved.png
PythonShujujiegouYuSuanfa/img/settings-s.png
PythonShujujiegouYuSuanfa/img/settings.png
PythonShujujiegouYuSuanfa/img/star.png
PythonShujujiegouYuSuanfa/js/__init__.py
PythonShujujiegouYuSuanfa/js/epub.js
PythonShujujiegouYuSuanfa/js/epub.min.js
PythonShujujiegouYuSuanfa/js/epub.min.map
PythonShujujiegouYuSuanfa/js/hooks.min.js
PythonShujujiegouYuSuanfa/js/hooks.min.map
PythonShujujiegouYuSuanfa/js/reader.js
PythonShujujiegouYuSuanfa/js/reader.js.map
PythonShujujiegouYuSuanfa/js/reader.min.js
PythonShujujiegouYuSuanfa/js/reader.min.map
PythonShujujiegouYuSuanfa/js/hooks/__init__.py
PythonShujujiegouYuSuanfa/js/hooks/extensions/__init__.py
PythonShujujiegouYuSuanfa/js/hooks/extensions/highlight.js
PythonShujujiegouYuSuanfa/js/libs/__init__.py
PythonShujujiegouYuSuanfa/js/libs/jquery.min.js
PythonShujujiegouYuSuanfa/js/libs/localforage.min.js
python_shujujiegou_yu_suanfa-2024.3.1.0.dist-info/METADATA
python_shujujiegou_yu_suanfa-2024.3.1.0.dist-info/WHEEL
python_shujujiegou_yu_suanfa-2024.3.1.0.dist-info/entry_points.txt
python_shujujiegou_yu_suanfa-2024.3.1.0.dist-info/top_level.txt
python_shujujiegou_yu_suanfa-2024.3.1.0.dist-info/RECORD
